linq4py/__init__.py
linq4py/core.py
linq4py/exceptions.py
linq4py/linq4py.py
linq4py-1.0.3.dist-info/LICENSE
linq4py-1.0.3.dist-info/METADATA
linq4py-1.0.3.dist-info/WHEEL
linq4py-1.0.3.dist-info/RECORD
