Metadata-Version: 2.1
Name: linq4py
Version: 1.0.3
Summary: Linq for python
Keywords: LINQ,linq for python
Author: six006
Author-email: six006@126.com
Requires-Python: >=3.10
Classifier: Programming Language :: Python :: 3
Classifier: Programming Language :: Python :: 3.10
Classifier: Programming Language :: Python :: 3.11
